intermodule/__init__.py
intermodule/intermodule.py
intermodule-1.0.0.post1.dist-info/METADATA
intermodule-1.0.0.post1.dist-info/WHEEL
intermodule-1.0.0.post1.dist-info/RECORD
