Metadata-Version: 2.4
Name: intermodule
Version: 1.0.0.post1
Summary: Share global variables across modules
Project-URL: Homepage, https://github.com/pyhacks/intermodule
Author-email: pyhacks <enginyildirim111@gmail.com>
Keywords: global,inter,module,shared
Requires-Dist: assign-overload
Requires-Dist: wrapt
